[
  {
    "ContainingType": "GamingClub.Server.Controllers.AboutController",
    "Method": "Index",
    "RelativePath": "About",
    "HttpMethod": "GET",
    "IsController": true,
    "Order": 0,
    "Parameters": [],
    "ReturnTypes": []
  },
  {
    "ContainingType": "GamingClub.Server.Controllers.GamingStationsController",
    "Method": "GetGamingStationsAsync",
    "RelativePath": "api/GamingStations",
    "HttpMethod": "GET",
    "IsController": true,
    "Order": 0,
    "Parameters": [],
    "ReturnTypes": []
  },
  {
    "ContainingType": "GamingClub.Server.Controllers.ReservationsController",
    "Method": "GetReservationByIdAsync",
    "RelativePath": "api/Reservations/{id}",
    "HttpMethod": "GET",
    "IsController": true,
    "Order": 0,
    "Parameters": [
      {
        "Name": "id",
        "Type": "System.Int32",
        "IsRequired": true
      }
    ],
    "ReturnTypes": [],
    "EndpointName": "GetReservationById"
  },
  {
    "ContainingType": "GamingClub.Server.Controllers.ReservationsController",
    "Method": "CreateReservation",
    "RelativePath": "api/Reservations/CreateReservation",
    "HttpMethod": "POST",
    "IsController": true,
    "Order": 0,
    "Parameters": [
      {
        "Name": "reservationDTO",
        "Type": "GamingClub.Application.DTOs.Reservation.ReservationDTO",
        "IsRequired": true
      }
    ],
    "ReturnTypes": []
  },
  {
    "ContainingType": "GamingClub.Server.Controllers.ReservationsController",
    "Method": "UpdateReservation",
    "RelativePath": "api/Reservations/UpdateReservation/{id}",
    "HttpMethod": "PUT",
    "IsController": true,
    "Order": 0,
    "Parameters": [
      {
        "Name": "reservationDTO",
        "Type": "GamingClub.Application.DTOs.Reservation.ReservationUpdateDTO",
        "IsRequired": true
      },
      {
        "Name": "id",
        "Type": "System.Int32",
        "IsRequired": true
      }
    ],
    "ReturnTypes": []
  },
  {
    "ContainingType": "GamingClub.Server.Controllers.UsersController",
    "Method": "GetUserById",
    "RelativePath": "api/Users/{id}",
    "HttpMethod": "GET",
    "IsController": true,
    "Order": 0,
    "Parameters": [
      {
        "Name": "id",
        "Type": "System.Int32",
        "IsRequired": true
      }
    ],
    "ReturnTypes": [],
    "EndpointName": "GetUserById"
  },
  {
    "ContainingType": "GamingClub.Server.Controllers.UsersController",
    "Method": "CreateUser",
    "RelativePath": "api/Users/CreateUser",
    "HttpMethod": "POST",
    "IsController": true,
    "Order": 0,
    "Parameters": [
      {
        "Name": "user",
        "Type": "GamingClub.Application.DTOs.User.UserDTO",
        "IsRequired": true
      }
    ],
    "ReturnTypes": []
  },
  {
    "ContainingType": "GamingClub.Server.Controllers.UsersController",
    "Method": "DeleteUser",
    "RelativePath": "api/Users/DeleteUserById",
    "HttpMethod": "DELETE",
    "IsController": true,
    "Order": 0,
    "Parameters": [
      {
        "Name": "id",
        "Type": "System.Int32",
        "IsRequired": false
      }
    ],
    "ReturnTypes": []
  },
  {
    "ContainingType": "GamingClub.Server.Controllers.UsersController",
    "Method": "GetUserFromFile",
    "RelativePath": "api/Users/FromFile/{id}",
    "HttpMethod": "GET",
    "IsController": true,
    "Order": 0,
    "Parameters": [
      {
        "Name": "id",
        "Type": "System.Int32",
        "IsRequired": true
      }
    ],
    "ReturnTypes": []
  },
  {
    "ContainingType": "GamingClub.Server.Controllers.UsersController",
    "Method": "GetUserWithReservations",
    "RelativePath": "api/Users/GetUserWithReservations/{id}",
    "HttpMethod": "GET",
    "IsController": true,
    "Order": 0,
    "Parameters": [
      {
        "Name": "id",
        "Type": "System.Int32",
        "IsRequired": true
      }
    ],
    "ReturnTypes": []
  },
  {
    "ContainingType": "GamingClub.Server.Controllers.UsersController",
    "Method": "UpdateUser",
    "RelativePath": "api/Users/UpdateUser/{id}",
    "HttpMethod": "PUT",
    "IsController": true,
    "Order": 0,
    "Parameters": [
      {
        "Name": "user",
        "Type": "GamingClub.Application.DTOs.User.UserUpdateDTO",
        "IsRequired": true
      },
      {
        "Name": "id",
        "Type": "System.Int32",
        "IsRequired": true
      }
    ],
    "ReturnTypes": []
  },
  {
    "ContainingType": "GamingClub.Server.Controllers.HomeController",
    "Method": "Index",
    "RelativePath": "Home",
    "HttpMethod": "GET",
    "IsController": true,
    "Order": 0,
    "Parameters": [],
    "ReturnTypes": []
  },
  {
    "ContainingType": "GamingClub.Server.Controllers.TournamentsController",
    "Method": "Index",
    "RelativePath": "Tournaments",
    "HttpMethod": "GET",
    "IsController": true,
    "Order": 0,
    "Parameters": [],
    "ReturnTypes": []
  }
]